digifoam/__init__.py
digifoam/api.py
digifoam/cli.py
digifoam/constants.py
digifoam/types.py
digifoam/utils.py
digifoam-0.2.0.dist-info/LICENSE
digifoam-0.2.0.dist-info/METADATA
digifoam-0.2.0.dist-info/WHEEL
digifoam-0.2.0.dist-info/entry_points.txt
digifoam-0.2.0.dist-info/top_level.txt
digifoam-0.2.0.dist-info/RECORD
