Metadata-Version: 2.1
Name: digifoam
Version: 0.2.0
Summary: DigiFOAM CLI
Home-page: https://digifoam.ai
Author: Michael
Author-email: michael@digitalcarbon.ai
Classifier: Programming Language :: Python :: 3
Classifier: License :: OSI Approved :: MIT License
Classifier: Operating System :: OS Independent
Requires-Python: >=3.7
License-File: LICENSE
Requires-Dist: click
Requires-Dist: python-dotenv
Requires-Dist: requests
Requires-Dist: chardet
Requires-Dist: typer
Requires-Dist: websockets
